offres_emploi/__init__.py
offres_emploi/api.py
offres_emploi/utils.py
api_offres_emploi-0.0.1.dist-info/LICENSE
api_offres_emploi-0.0.1.dist-info/METADATA
api_offres_emploi-0.0.1.dist-info/WHEEL
api_offres_emploi-0.0.1.dist-info/top_level.txt
api_offres_emploi-0.0.1.dist-info/RECORD
