Metadata-Version: 2.1
Name: api-offres-emploi
Version: 0.0.1
Summary: Python interface to 'API Offres d'emploi v2' (Pole Emploi job search API)
Home-page: https://github.com/etiennekintzler/api-offres-emploi
Author: Etienne Kintzler
Author-email: etienne.kintzler@gmail.com
License: UNKNOWN
Platform: UNKNOWN
Classifier: Programming Language :: Python :: 3
Classifier: License :: OSI Approved :: MIT License
Classifier: Operating System :: OS Independent
Requires-Python: >=3.6
